ch_package/__init__.py
ch_package/ch_package.py
ch_package-0.1.2.dist-info/LICENSE.txt
ch_package-0.1.2.dist-info/METADATA
ch_package-0.1.2.dist-info/WHEEL
ch_package-0.1.2.dist-info/top_level.txt
ch_package-0.1.2.dist-info/RECORD
