Metadata-Version: 2.1
Name: ch-package
Version: 0.1.2
Summary: This is a simple test project
Home-page: UNKNOWN
Author: Chaz
License: UNKNOWN
Platform: UNKNOWN
Classifier: License :: OSI Approved :: MIT License
Classifier: Operating System :: OS Independent
Requires-Python: >=3.5
License-File: LICENSE.txt
